{
  "status": "success",
  "totalResults": 1,
  "results": [
    {
      "title": "THE GUNDAM BASE Expands Across North America with Two New U.S. Locations Opening in 2026",
      "description": "New stores coming to Minneapolis and Seattle following the success of THE GUNDAM BASE Chicago IRVINE, Calif., July 23, 2026 /PRNewswire/ \u2014 Bandai Namco Amusement America Inc. (\u201cBNAA\u201d) and Bandai Namco Toys & Collectibles America Inc. (\u201cBNTCA\u201d) are excited to announce the continued expansion of THE GUNDAM BASE in the United States with two new [...]",
      "link": "https://celebrityhint.com/the-gundam-base-expands-across-north-america-with-two-new-u-s-locations-opening-in-2026/",
      "source": "Celebrity Hint",
      "image": "https://celebrityhint.com/wp-content/themes/publisher/images/default-thumb/large.png",
      "published": "2026-07-23 21:19:00",
      "category": [
        "technology",
        "top"
      ],
      "country": [
        "india"
      ]
    }
  ]
}