{
  "status": "success",
  "totalResults": 2,
  "results": [
    {
      "title": "Wichita-area girls wrestlers make history with two Fargo national titles",
      "description": "Maize\u2019s Gray Joyce has her arm raised after winning the 145-pound national championship in the 16U girls freestyle division at the U.S. Marine Corps Junior Nationals in Fargo, N.D.",
      "link": "https://www.kansas.com/sports/varsity-kansas/other-varsity-sports/article316574476.html",
      "source": "Wichita Eagle",
      "image": "https://www.kansas.com/public/sports/college/wichita-state/41drsv/picture316574481/alternates/FREE_1140/750865372_1008413195525406_7129532276394293484__fitted.jpeg",
      "published": "2026-07-20 12:01:00",
      "category": [
        "top",
        "sports"
      ],
      "country": [
        "united states of america"
      ]
    },
    {
      "title": "Verstappen encouraged by Spa performance despite 'unlucky' VSC costing him a chance at second",
      "description": "Max Verstappen was upbeat after the Belgian Grand Prix despite a Virtual Safety Car costing him a chance at a better result.",
      "link": "https://racer.com/2026/07/20/verstappen-encouraged-by-spa-performance-despite-unlucky-vsc-costing-him-a-chance-at-second",
      "source": "Racer",
      "image": "https://cdn-cs-images.racer.com/v3/assets/blte77f57883ea46be1/blte3cf38defea2c1b0/6a5e12f7745c9544743acb19/GettyImages-2286753838.jpg?environment=live",
      "published": "2026-07-20 12:00:58",
      "category": [
        "sports"
      ],
      "country": [
        "united states of america"
      ]
    }
  ]
}