{
  "status": "success",
  "totalResults": 19,
  "results": [
    {
      "title": "The Bromley and Bexley trains cancelled by works this week",
      "description": "Several Southeastern trains will be cancelled, diverted, or replaced by buses this week.",
      "link": "https://www.london-now.co.uk/news/26175173.bromley-bexley-trains-affected-works-week/",
      "source": "This Is Local London",
      "image": "https://www.london-now.co.uk/resources/images/20490539/",
      "published": "2026-06-08 12:04:00",
      "category": [
        "crime",
        "top"
      ],
      "country": [
        "united kingdom"
      ]
    },
    {
      "title": "$110K raised as Kelowna fundraiser for autism grows into national movement",
      "description": "People can participate in local paddling events raising money for Autism Canada through June",
      "link": "https://pentictonwesternnews.com/2026/06/08/110k-raised-as-kelowna-fundraiser-for-autism-grows-into-national-movement/",
      "source": "Penticton Western News",
      "image": "https://pentictonwesternnews.com/wp-content/uploads/sites/11/2026/06/42508857_web1_260611-KCN-Waves-for-Autism_1.jpg",
      "published": "2026-06-08 12:04:00",
      "category": [
        "lifestyle",
        "top"
      ],
      "country": [
        "canada"
      ]
    },
    {
      "title": "$110K raised as Kelowna fundraiser for autism grows into national movement",
      "description": "People can participate in local paddling events raising money for Autism Canada through June",
      "link": "https://vernonmorningstar.com/2026/06/08/110k-raised-as-kelowna-fundraiser-for-autism-grows-into-national-movement/",
      "source": "Vernon Morning Star",
      "image": "https://vernonmorningstar.com/wp-content/uploads/sites/4/2026/06/42508857_web1_260611-KCN-Waves-for-Autism_1.jpg",
      "published": "2026-06-08 12:04:00",
      "category": [
        "lifestyle",
        "top"
      ],
      "country": [
        "canada"
      ]
    },
    {
      "title": "$110K raised as Kelowna fundraiser for autism grows into national movement",
      "description": "People can participate in local paddling events raising money for Autism Canada through June",
      "link": "https://wltribune.com/2026/06/08/110k-raised-as-kelowna-fundraiser-for-autism-grows-into-national-movement/",
      "source": "Williams Lake Tribune",
      "image": "https://wltribune.com/wp-content/uploads/sites/6/2026/06/42508857_web1_260611-KCN-Waves-for-Autism_1.jpg",
      "published": "2026-06-08 12:04:00",
      "category": [
        "lifestyle",
        "top"
      ],
      "country": [
        "canada"
      ]
    },
    {
      "title": "Cyberport Chairman Joined CE's Business Delegation to Kazakhstan and Uzbekistan",
      "description": "Partnership with the Countries' Largest Tech Parks to Propel \"Hub-to-Hub\" Collaborations Supporting HK and Chinese Mainland Enterprises to Tap Central Asian Markets HONG KONG SAR - Media OutReach Newswire - 8 June 2026 - Simon Chan, Chairman of Cyberport, joined the business delegation led by Chief Executive John Lee, on a visit to Kazakhstan and Uzbekistan from 1 to 5 June 2026 to strengthen innovation technology (IT), economic and trade cooperation between Hong Kong and the Central Asia. During the visit, Cyberport signed Memoranda of Understanding (MoUs) with leading technology organisations in both Kazakhstan and Uzbekistan, establishing strategic partnerships with the two countries' key innovation and technology platforms and promoting \"hub-to-hub\" collaboration to jointly capture opportunities in emerging markets. As part of the programme, Simon Chan, Chairman of Cyberport, met with key innovation and technology stakeholders in both countries. He visited the Astana Hub, a local technology and innovation park in Kazakhstan, including its Artificial Intelligence Supercomputing Centre, to gain deeper insights into the latest developments in artificial intelligence and digital infrastructure in the region. He also visited IT Park Uzbekistan to learn more about the country's rapidly growing digital economy ecosystem, and to explore opportunities for deeper collaboration in innovation and technology development, talent cultivation and market expansion. These engagements further strengthened Hong Kong's exchanges with Central Asia and supported the development of closer cross-regional collaboration in innovation and technology. Simon Chan, Chairman of Cyberport, said, \"Central Asia is a strategically important market under the Belt and Road Initiative. Both Kazakhstan and Uzbekistan are actively advancing digital transformation, digital upgrading and technological innovation. From national artificial intelligence development blueprints to large-scale digital infrastructure projects, both countries have demonstrated strong growth momentum, a pressing demand for cutting-edge innovation and technology solutions, and immense market potential. As Hong Kong's digital technology hub and AI accelerator, Cyberport is home to over 2,300 companies, including 18 listed companies with a combined market capitalisation of over HK$500 billion, as well as 9 unicorns with a total valuation exceeding HK$150 billion. Its innovation ecosystem spans areas such as AI, data science, fintech, digital assets and blockchain, cybersecurity, smart living, and digital entertainment. This aligns closely with Central Asia's demand for technological innovation, creating extensive opportunities for collaboration through complementary strengths. Cyberport has also established partnerships with Astana Hub and IT Park Uzbekistan to actively promote bilateral business expansion, deepen ties between Hong Kong and Central Asia in innovation and technology, finance and trade, and support enterprises from Hong Kong and the Mainland in jointly expanding into high-potential emerging markets. Leveraging Hong Kong's unique role as a 'super-connector' and 'super value-adder', Cyberport will continue to support Hong Kong and Mainland enterprises in expanding into Belt and Road and international markets. At the same time, we will actively attract Central Asian companies to establish a presence in Hong Kong, injecting fresh momentum into the development of the digital economy and smart cities across the three regions, and further strengthening Hong Kong's position as an international innovation and technology centre and a leading AI hub.\" Simon Chan, Chairman of Cyberport, said, \"Central Asia is a strategically important market under the Belt and Road Initiative. Both Kazakhstan and Uzbekistan are actively advancing digital transformation, digital upgrading and technological innovation. Cyberport has established partnerships with Kazakhstan Astana Hub and IT Park Uzbekistan to actively promote bilateral business expansion, deepen ties between Hong Kong and Central Asia in innovation and technology, finance and trade, and support enterprises from Hong Kong and the Mainland in jointly expanding into high-potential emerging markets.\" Signs MoUs with the Countries' Largest Tech Parks Leveraging \"Hub-to-Hub\" Collaboration Advantages Among them was a Memorandum of Understanding (MoU) signed on 1 June 2026 between Cyberport and Autonomous Cluster Fund \"Astana Hub\" (Astana Hub) of Kazakhstan, the largest international innovation cluster in Central Eurasia. Astana Hub is currently home to more than 1,800 IT companies, including over 450 international members, generating a collective income of US$3.9 billion. It has established a comprehensive innovation ecosystem that provides acceleration programmes, supports technological business incubation, offers educational initiatives, and hosts a wide range of industry events. This strategic partnership aims to promote technology transfer, support tech companies in areas such as AI, fintech, smart city solutions and Web 3, and facilitate overseas expansion and global market access for innovation and technology companies from both regions. Another key highlight of the delegation was the signing of a Memorandum of Understanding (MoU) on 4 June 2026 between Cyberport and The Administration of Technology Park of Software and IT (IT Park) of Uzbekistan, a national IT ecosystem operator dedicated to advancing the country's digital industry development. IT Park Uzbekistan is a government-supported technology hub and one of the largest tech parks in Central Asia, with more than 2,800 member companies spanning IT services, software development, game development, creative industries and education. The MoU focuses on providing mutual soft-landing support, infrastructure access and regulatory incentives to facilitate technology companies' expansion between Hong Kong and Central Asian markets, while fostering deeper collaboration in innovation and technology development between the two regions. As an ideal gateway for Central Asian technology companies seeking to expand into East and Southeast Asia, Cyberport leverages Hong Kong's international business environment and robust regulatory framework, together with its extensive network of enterprises, investors, technology companies, professional service providers and industry partners. This enables Cyberport to serve as a strategic base for Central Asian enterprises looking to access the Mainland, ASEAN, Asia-Pacific and global markets, accelerating their commercialisation journey and transforming innovative solutions into tangible business collaborations and investment opportunities. At the same time, Cyberport companies can leverage the two leading technology parks in Central Asia as launchpads into emerging markets, bringing technology solutions from Hong Kong such as artificial intelligence, fintech and smart city technologies to support the region's digital economy and smart city development. These collaborations will further enrich the innovation and technology ecosystems of both regions. Cyberport has been actively supporting local enterprises in establishing and expanding their presence in Central Asian market. Cyberport's community is also highly international, with founders of one-third of its onsite companies coming from 27 countries and regions, while Cyberport companies have expanded into more than 35 global markets. Cyberport received delegations from Kazakhstan and Uzbekistan to Cyberport for exchanges in tech innovation and entrepreneurship over the past year, laying foundations for cross-regional partnerships and collaborations. Cyberport will continue to align with the national 15th Five-Year Plan and support the HKSAR Government's development strategies by strengthening ties with emerging markets and innovation and technology hubs along the Belt and Road. As a vital bridge between Hong Kong and Central Asia, Cyberport facilitates cross-regional exchanges and collaboration, helping local enterprises capture global business opportunities while simultaneously attracting outstanding overseas technology talent and leading enterprises to establish a presence in Hong Kong. These efforts will inject diversified momentum into Hong Kong's economy and further reinforce the city's position as an international innovation and technology hub. About Hong Kong Cyberport Wholly owned by the Hong Kong Special Administrative Region (HKSAR) Government, Cyberport is Hong Kong's digital tech hub and AI accelerator, with a vision to empower industry digitalisation and intelligent transformation, to promote digital economy and AI development, and to foster Hong Kong to be an international AI, innovation and technology (I&T) hub. Cyberport gathers over 2,300 companies, including 18 listed companies and 9 unicorns. One-third of onsite companies' founders come from 27 countries and regions, while Cyberport companies have expanded to over 35 global markets. Cyberport, with Hong Kong's largest AI Supercomputing Centre and AI Lab as the engine, has been building the AI ecosystem with industry-leading AI companies and over 500 AI and data science start-ups. Through development of tech clusters, namely AI, data science, blockchain and cybersecurity, Cyberport empowers industries across smart city and government, banking and finance, digital entertainment, culture and tourism, healthcare, education and training, property management, construction, transportation and logistics, green environment and more, while hosting Hong Kong's largest FinTech community. Commissioned by the HKSAR Government, Cyberport has implemented proof-of-concept and sandbox schemes, subsidisation for digital tech adoption, industry tech training and start-up incubation, to drive technology R&D, translation and commercialisation, thus propelling digital transformation and intelligent upgrade across industry and society. Also as \"State-level Scientific and Technological Enterprise Incubator\" and Hong Kong's key incubator, Cyberport supports entrepreneurs with funding and office space, extensive networks of enterprises, investors, technology corporations and professional services for business growth and expansion to Chinese Mainland and overseas markets, all-round facilitation for landing in Hong Kong, talent attraction and cultivation, ready as a launchpad to take start-ups in any stages of development to the next level. For more information, please visit https://www.cyberport.hk/en The issuer is solely responsible for the content of this announcement. Hashtags: #Cyberport",
      "link": "https://www.riauone.com/global/Cyberport-Chairman-Joined-CE--039-s-Business-Delegation-to-Kazakhstan-and-Uzbekistan",
      "source": "Riauone.com | Berita Nusantara Terkini",
      "image": "https://www.riauone.com/photo/berita/dir062026/3672_Cyberport-Chairman-Joined-CE--039-s-Business-Delegation-to-Kazakhstan-and-Uzbekistan.jpg",
      "published": "2026-06-08 12:04:00",
      "category": [
        "technology",
        "top"
      ],
      "country": [
        "indonesia"
      ]
    },
    {
      "title": "$110K raised as Kelowna fundraiser for autism grows into national movement",
      "description": "People can participate in local paddling events raising money for Autism Canada through June",
      "link": "https://kelownacapnews.com/2026/06/08/110k-raised-as-kelowna-fundraiser-for-autism-grows-into-national-movement/",
      "source": "Kelowna Capital News",
      "image": "https://kelownacapnews.com/wp-content/uploads/sites/5/2026/06/42507052_web1_260611-KCN-Waves-for-Autism_1.jpg",
      "published": "2026-06-08 12:04:00",
      "category": [
        "lifestyle",
        "top"
      ],
      "country": [
        "canada"
      ]
    },
    {
      "title": "TransCode Therapeutics to Host R&D Webcast on June 18, 2026",
      "description": "Live Webcast to Highlight TTX-MC138 Phase 2a Trial, Three-Platform Pipeline, and Investment Thesis BOSTON, June 8, 2026 /PRNewswire/ -- TransCode Therapeutics, Inc. (NASDAQ: RNAZ), a clinical-stage oncology company advancing a three-platform pipeline in RNA therapeutics and...",
      "link": "https://www.prnewswire.com/news-releases/transcode-therapeutics-to-host-rd-webcast-on-june-18-2026-302793483.html",
      "source": "Pr Newswire",
      "image": "https://mmx.prnewswire.com/media/MS1773301/TransCode_Therapeutics_Inc.jpg?id=OA2690167&p=original",
      "published": "2026-06-08 12:04:00",
      "category": [
        "technology",
        "top"
      ],
      "country": [
        "united states of america"
      ]
    },
    {
      "title": "$110K raised as Kelowna fundraiser for autism grows into national movement",
      "description": "People can participate in local paddling events raising money for Autism Canada through June",
      "link": "https://terracestandard.com/2026/06/08/110k-raised-as-kelowna-fundraiser-for-autism-grows-into-national-movement/",
      "source": "Terrace Standard",
      "image": "https://terracestandard.com/wp-content/uploads/sites/13/2026/06/42508857_web1_260611-KCN-Waves-for-Autism_1.jpg",
      "published": "2026-06-08 12:04:00",
      "category": [
        "lifestyle",
        "top"
      ],
      "country": [
        "canada"
      ]
    },
    {
      "title": "Homeowners urged to stop using extension leads in 1 room 'now'",
      "description": "Fire safety specialists at Crusader Fire are urging UK homeowners who use extension leads to 'make a decision fast'",
      "link": "https://www.express.co.uk/news/uk/2214751/homeowners-urged-stop-using-extension-leads-1-room",
      "source": "Express",
      "image": "https://cdn.images.express.co.uk/img/dynamic/1/590x/2214751_1.jpg",
      "published": "2026-06-08 12:04:00",
      "category": [
        "crime",
        "top"
      ],
      "country": [
        "united kingdom"
      ]
    },
    {
      "title": "Man accused of calling 911 during traffic stop in Lee County, resisting arrest",
      "description": null,
      "link": "https://www.gulfcoastnewsnow.com/article/911-called-during-traffic-stop-lee-county-arrest/71522021",
      "source": "Wbbh",
      "image": "https://hips.hearstapps.com/htv-prod/images/2551563e-5643-4546-9f92-4d33b43fc96e.png",
      "published": "2026-06-08 12:04:00",
      "category": [
        "crime",
        "top"
      ],
      "country": [
        "united states of america"
      ]
    },
    {
      "title": "Repubblika calls for Chief Justice talks to resume, wants judiciary to be responsible for selection",
      "description": "Civil society group Repubblika stated Monday that now that the general election has passed, it is time for the government and opposition to resume discussions on who should be the country's next Chief Justice. The NGO also called for the selection of the Chief Justice to fall in the hands of the judiciary, after the selection of the next Chief Justice devolved into a public political quarrel between the two major party leaders, Prime Minister Robert Abela and Opposition leader Alex Borg. Chief Justice Mark Chetcuti has continued in his role in spite of reaching retirement age after the two sides of the House failed to come to terms on his successor. Repubblika said that \"the need to appoint a Chief Justice did not end because the election has passed.\" It added that now that \"electoral pressures have passed, we have an opportunity to address this issue with the seriousness it deserves.\" Repubblika believes that the public discussion on appointing a new Chief Justice should focus on the selection process, rather than on potential candidates for the constitutional post. It noted that since the office of the Chief Justice is not a political office, \"the person who heads the judiciary should not be selected through public competition between political parties, nor should their appointment become another occasion for partisan polemics.\" \"The independence and authority of the judiciary are not strengthened when judges are discussed as if they are political candidates,\" Repubblika stated. The NGO remarked that with the judiciary being a separate branch from the State, it is \"reasonable that the members of the judiciary should have a decisive role in the selection of the person who leads them.\" It added that even European institutions have called for the judiciary's role in this selection process to be empowered. \"The aim should not be to reach a political agreement behind the scenes or after a public pantomime, but that the appointment is as free as possible from political interference and enjoys the trust of the judiciary itself,\" Repubblika issued in its statement. The civil society group concluded that \"there is no reason for this discussion to remain mired in partisan calculations\" and that \"Before Malta is once again lost in speculation on individual names, we should have a mature discussion about the principles that should govern the appointment of a Chief Justice.\" Repubblika ultimately hopes for the appointment process of Malta's Chief Justice to strengthen the judiciary's independence, strengthen public confidence in the courts, and better guarantee the separation of powers. Chief Justice Mark Chetcuti was scheduled to vacate his post on his 68 th birthday, on 4 February 2026. Instead of selecting his successor however, Prime Minister Abela and PN leader Borg were caught at a very publicised impasse. This boiled over when Judge Wenzu Mintoff accused the Prime Minister of prioritising money and political calculation over judicial independence in a five-page letter sent to the Cabinet Secretary, in which he wrote, under oath, that PM Abela did not want to appoint him as the next Chief Justice so as not to please the Nationalist Party, who had listed him as one of its four preferred candidates. Judge Mintoff had alleged that Abela told him that he preferred to delay naming a new Chief Justice till after the next general election - this was before the country knew that an early general election would happen on 30 May 2026. Chief Justice Chetcuti was forced to stay on as Chief Justice till consensus can be reached on who should be his successor. The Nationalist Party Opposition blocked two of the government's Chief Justice nominations in Parliament. Judge Consuelo Scerri Herrera's nomination was blocked by the Opposition on what should have been Chetcuti's final day in this role. The Opposition then rejected the government's second Chief Justice nomination - Judge Myriam Hayman - at the end of February. A two-thirds voting majority is required in Parliament for a consensus to be achieved on who should be the next Chief Justice. As a result of this impasse, a bill proposing the introduction of an anti-deadlock mechanism for the appointment of Malta's Chief Justice was tabled in Parliament's agenda in early March. The Chief Justice is responsible for assigning magistrates to preside over distinct kinds of cases, as well as hearing constitutional and appeal cases, and is effectively viewed as the head of the Maltese judiciary. Similarly to this ordeal, the Maltese islands are also pending the appointment of a new Auditor General. AG Charles Deguara was similarly forced to remain in his post till a successor is selected by the country's MPs when Parliament unanimously voted, earlier this March, to suspend its deadline to appoint a new Auditor General. This constitutional role also requires a two-thirds cross-party consensus. AG Deguara was set to vacate his post on 30 March. Before Malta can appoint a new Chief Justice and Auditor General, Parliament must be formed, following casual elections and gender corrective mechanism additions to the House of Representatives, and convene to discuss these pending matters.",
      "link": "https://www.independent.com.mt/articles/2026-06-08/local-news/Repubblika-calls-for-Chief-Justice-talks-to-resume-wants-judiciary-to-be-responsible-for-selection-6736290341",
      "source": "Malta Independent",
      "image": null,
      "published": "2026-06-08 12:04:00",
      "category": [
        "politics",
        "top"
      ],
      "country": [
        "malta"
      ]
    },
    {
      "title": "The Bromley and Bexley trains cancelled by works this week",
      "description": "Several Southeastern trains will be cancelled, diverted, or replaced by buses this week.",
      "link": "https://www.newsshopper.co.uk/news/26175173.bromley-bexley-trains-affected-works-week/",
      "source": "Newsshopper Co Uk",
      "image": null,
      "published": "2026-06-08 12:04:00",
      "category": [
        "crime",
        "top"
      ],
      "country": [
        "united kingdom"
      ]
    },
    {
      "title": "$110K raised as Kelowna fundraiser for autism grows into national movement",
      "description": "People can participate in local paddling events raising money for Autism Canada through June",
      "link": "https://saobserver.net/2026/06/08/110k-raised-as-kelowna-fundraiser-for-autism-grows-into-national-movement/",
      "source": "Salmon Arm Observer",
      "image": "https://saobserver.net/wp-content/uploads/sites/10/2026/06/42508857_web1_260611-KCN-Waves-for-Autism_1.jpg",
      "published": "2026-06-08 12:04:00",
      "category": [
        "lifestyle",
        "top"
      ],
      "country": [
        "canada"
      ]
    },
    {
      "title": "Rekha Gupta-led Delhi govt signs key MoA to support dust-free roads",
      "description": "The initiative is expected to strengthen pollution control and contribute to a cleaner, greener, and more sustainable Delhi. Cabinet ministers Parvesh Sahib Singh and Manjinder Singh Sirsa were present on the occasion.",
      "link": "https://www.dnaindia.com/delhi-ncr/report-chief-minister-rekha-gupta-led-delhi-government-signs-key-moa-to-support-dust-free-roads-pwd-spa-csir-crri-yamuna-riverfront-cleanliness-campaign-3212755",
      "source": "Dna",
      "image": "https://cdn.dnaindia.com/sites/default/files/styles/full/public/2026/06/08/2750968-rekha-gupta-1.png",
      "published": "2026-06-08 12:04:00",
      "category": [
        "environment",
        "top"
      ],
      "country": [
        "india"
      ]
    },
    {
      "title": "Delhi hotel fire: Court extends owner's police custody by two days",
      "description": "New Delhi Fire: Owner's custody extended; 22 killed in hotel blaze. Court remands another accused in deadly fire investigation.",
      "link": "https://www.deccanherald.com/india/delhi/delhi-hotel-fire-court-extends-owners-police-custody-by-two-days-4031523",
      "source": "Deccan Herald",
      "image": "https://media.assettype.com/deccanherald/2026-06-08/rcsm35z4/file86508058klkxsb641im.jpg?w=1200&h=675&auto=format%2Ccompress&fit=max&enlarge=true",
      "published": "2026-06-08 12:03:59",
      "category": [
        "crime",
        "top"
      ],
      "country": [
        "india"
      ]
    },
    {
      "title": "Eastbound Interstate 76 closed due to multiple-vehicle crash",
      "description": "The eastbound lanes of I-76 are closed after a multi-vehicle crash Monday morning, according to Colorado State Patrol.",
      "link": "https://www.9news.com/article/traffic/i-76-crash/73-3747ceb5-d830-4dbd-87c6-05daa6fc1da7",
      "source": "9news",
      "image": null,
      "published": "2026-06-08 12:03:58",
      "category": [
        "crime",
        "top"
      ],
      "country": [
        "australia"
      ]
    },
    {
      "title": "US tobacco giant moves into Dutch weed legalisation trial",
      "description": "A US tobacco giant is behind the planned take over of the Netherlands\u2019 biggest licensed cannabis grower, prompting fears among...",
      "link": "https://www.dutchnews.nl/2026/06/us-tobacco-giant-moves-into-dutch-weed-legalisation-trial/",
      "source": "Dutchnews",
      "image": null,
      "published": "2026-06-08 12:03:55",
      "category": [
        "health",
        "top"
      ],
      "country": [
        "netherland"
      ]
    },
    {
      "title": "Pakistan: Concerns raised over Rawalakot \u2018massacre\u2019, grim situation in PoK",
      "description": "Islamabad, June 8 (SocialNews.XYZ) The United Kashmir People's National Party (UKPNP) on Monday strongly condemned the firing by Pakistani security forces on peaceful and unarmed protesters in the Rawalakot region of Pakistan-occupied Kashmir (POK) that... The post Pakistan: Concerns raised over Rawalakot \u2018massacre\u2019, grim situation in PoK appeared first on Social News XYZ .",
      "link": "https://www.socialnews.xyz/2026/06/08/pakistan-concerns-raised-over-rawalakot-massacre-grim-situation-in-pok/",
      "source": "Social News Xyz",
      "image": "https://i0.wp.com/www.socialnews.xyz/wp-content/uploads/2026/06/08/954923888c4bef5aac363c4855c58029-scaled.jpg?fit=2560%2C1336&quality=80&zoom=1&ssl=1",
      "published": "2026-06-08 12:03:55",
      "category": [
        "politics",
        "top"
      ],
      "country": [
        "india"
      ]
    },
    {
      "title": "Lead Plaintiff Deadlines in Shareholder Class Action Lawsuits Against Calix, Inc. (CALX), ...",
      "description": "ATLANTA, June 08, 2026 (GLOBE NEWSWIRE) -- Holzer & Holzer, LLC reminds investors of the deadline to seek to be appointed lead plaintiff in the following class action lawsuits:",
      "link": "https://www.reflector.com/news/national/lead-plaintiff-deadlines-in-shareholder-class-action-lawsuits-against-calix-inc-calx/article_f3f6bad4-eb73-5eb6-be7e-f62a3b97b09f.html",
      "source": "Reflector",
      "image": null,
      "published": "2026-06-08 12:03:55",
      "category": [
        "business",
        "top"
      ],
      "country": [
        "united states of america"
      ]
    }
  ]
}