{
  "status": "success",
  "totalResults": 8,
  "results": [
    {
      "title": "Frankfort teams post strong showing at WV State Track and Field Meet",
      "description": "Frankfort teams post strong showing at WV State Track and Field Meet",
      "link": "https://www.wvnews.com/mineralnews/frankfort-teams-post-strong-showing-at-wv-state-track-and-field-meet/article_e1475392-2c7c-44af-b6fa-874331db135e.html",
      "source": "Wv News",
      "image": "https://bloximages.chicago2.vip.townnews.com/wvnews.com/content/tncms/custom/image/dd23b0fa-a76a-11ea-b298-6f7943d03f88.jpg",
      "published": "2026-05-27 11:15:00",
      "category": [
        "sports",
        "top"
      ],
      "country": [
        "united states of america"
      ]
    },
    {
      "title": "N.J. baseball family has over 3,000 combined coaching wins \u2014 and they\u2019re not done yet",
      "description": "They have the coaching gene. Legendary baseball family has racked up over 3,000 wins and almost 5,000 games",
      "link": "https://www.nj.com/highschoolsports/2026/05/nj-baseball-family-has-over-3000-combined-coaching-wins-and-theyre-not-done-yet.html",
      "source": "Nj",
      "image": "https://www.nj.com/resizer/v2/37SZLBSHTRHDZEUGNQ7FXDMA64.png?auth=1d1fa5feda4faa824dbde81cd806a9e47082880c5966d6dcca2ffdfc906e02ca&smart=true&height=1200",
      "published": "2026-05-27 11:15:00",
      "category": [
        "sports",
        "top"
      ],
      "country": [
        "united states of america"
      ]
    },
    {
      "title": "Prep talk: Will next season's state championships in baseball, softball produce few opt outs?",
      "description": "Several Southern Section and City Section teams will not be participating in state playoffs this season.",
      "link": "https://www.latimes.com/sports/highschool/story/2026-05-27/prep-talk-will-next-seasons-state-championships-in-baseball-softball-produce-few-opt-outs",
      "source": "Los Angeles Times",
      "image": "https://ca-times.brightspotcdn.com/dims4/default/954b438/2147483647/strip/false/crop/382x60+0+0/resize/382x60!/quality/75/?url=https%3A%2F%2Fcalifornia-times-brightspot.s3.amazonaws.com%2Fde%2F5f%2F46c2d05b430cbc6e775301df1062%2Flogo-full-black.png",
      "published": "2026-05-27 11:15:00",
      "category": [
        "sports"
      ],
      "country": [
        "united states of america"
      ]
    },
    {
      "title": "Jonah Jeovany Vasquez of Cathedral is going for Disney-like ending at state track championships",
      "description": "In his first season of track, Jonah Jeovany Vasquez of Cathedral High has qualified to run in the 1,600 at state finals.",
      "link": "https://www.latimes.com/sports/highschool/story/2026-05-27/jonah-jeovany-vasquez-going-for-disney-like-ending-at-state-track",
      "source": "Los Angeles Times",
      "image": "https://ca-times.brightspotcdn.com/dims4/default/954b438/2147483647/strip/false/crop/382x60+0+0/resize/382x60!/quality/75/?url=https%3A%2F%2Fcalifornia-times-brightspot.s3.amazonaws.com%2Fde%2F5f%2F46c2d05b430cbc6e775301df1062%2Flogo-full-black.png",
      "published": "2026-05-27 11:15:00",
      "category": [
        "sports"
      ],
      "country": [
        "united states of america"
      ]
    },
    {
      "title": "Virginia football's returning D-Linemen have chance to grow into All-ACC level players",
      "description": "Fisher Camac, Anthony Britton and Jason Hammond give Virginia football a strong foundation of returning D-Linemen, and those three have the chance to develop into all-league level players.",
      "link": "https://newsvirginian.com/sports/college/football/virginia-cavaliers/article_7d75afcc-a974-5d37-8304-563675b005a3.html",
      "source": "The News Virginian",
      "image": null,
      "published": "2026-05-27 11:15:00",
      "category": [
        "sports",
        "top"
      ],
      "country": [
        "united states of america"
      ]
    },
    {
      "title": "Rochester Honkers promotional nights to circle and players to know this summer",
      "description": "The Rochester Honkers open their 2026 season against the Eau Claire Express at 6:35 p.m. tonight at Mayo Field.",
      "link": "https://www.postbulletin.com/sports/rochester-honkers-promotional-nights-to-circle-and-players-to-know-this-summer",
      "source": "Post Bulletin",
      "image": "https://cdn.forumcomm.com/dims4/default/1f155bc/2147483647/resize/800x/quality/90/?url=https%3A%2F%2Ffcc-cue-exports-brightspot.s3.us-west-2.amazonaws.com%2Fpostbulletin%2Fbinary%2F8b912385bff290604b7aa52efec07b7e_binary_5142340.jpg",
      "published": "2026-05-27 11:15:00",
      "category": [
        "sports",
        "top"
      ],
      "country": [
        "united states of america"
      ]
    },
    {
      "title": "Zimbabwe: Azeez Brace Sinks Zimbabwe in Unity Cup Showdown",
      "description": "[New Zimbabwe] ZIMBABWE'S senior men's football team suffered a 2-0 defeat to Nigeria in their Unity Cup semi-final clash played at Valley Stadium in London on Tuesday evening.",
      "link": "https://allafrica.com/stories/202605270313.html",
      "source": "Allafrica Tanzania",
      "image": "https://cdn.allafrica.com/static/images/structure/aa-logo-rgba-no-text-square.png",
      "published": "2026-05-27 11:15:00",
      "category": [
        "sports"
      ],
      "country": [
        "tanzania"
      ]
    },
    {
      "title": "Virginia football's returning D-Linemen have chance to grow into All-ACC level players",
      "description": "Fisher Camac, Anthony Britton and Jason Hammond give Virginia football a strong foundation of returning D-Linemen, and those three have the chance to develop into all-league level players.",
      "link": "https://dailyprogress.com/sports/college/football/virginia-cavaliers/article_0ac62761-1503-43f7-8477-14dd04f5caf7.html",
      "source": "The Daily Progress",
      "image": null,
      "published": "2026-05-27 11:15:00",
      "category": [
        "sports",
        "top"
      ],
      "country": [
        "united states of america"
      ]
    }
  ]
}