{
  "status": "success",
  "totalResults": 1,
  "results": [
    {
      "title": "240 athletes participate in Dimapur District Taekwondo C\u2019ship",
      "description": "Dimapur, June 15 (MExN): A total of 240 players participated in the Dimapur District Taekwondo Championship organised by the Dimapur District Taekwondo Association (DDTA) at the Multi-Disciplinary Sports Complex near DC Court Junction.The championship witnessed participation from taekwondo athletes across various age groups and weight categories, with competitors vying for top honours and qualification to the state-level tournament.According to the organisers, gold medallists from the district championship have been selected to represent Dimapur at the 36th Nagaland State Taekwondo Championship, scheduled to be held from July 28 to 30 at IG Stadium, Kohima.",
      "link": "https://morungexpress.com/240-athletes-participate-in-dimapur-district-taekwondo-cship",
      "source": "Morungexpress",
      "image": "https://morungexpress.com/uploads/2026/06/45231392_1781538828_Dimapur%20District%20Taekwondo%20Association.jpg",
      "published": "2026-06-15 15:53:48",
      "category": [
        "top",
        "sports"
      ],
      "country": [
        "india"
      ]
    }
  ]
}