{
  "status": "success",
  "totalResults": 1,
  "results": [
    {
      "title": "What The Tech: Waterllama Makes Drinking Water Feel Less Like a Chore",
      "description": "We track almost everything now. Steps. Sleep. Calories. Screen time. Packages. Even how many minutes we spend scrolling through apps we only opened to \u201ccheck one thing.\u201d",
      "link": "https://www.wrdw.com/2026/07/07/what-tech-waterllama-makes-drinking-water-feel-less-like-chore/",
      "source": "Https://www.wrdw.com",
      "image": "https://gray-wrdw-prod.gtv-cdn.com/resizer/v2/R6G4W3GWMVA6NPMZBXWUB2ZH2U.jpg?auth=5040bd3a0c6fcad8ffc2de3e92b12ffd90dc2af66e0194a6ed869f10aca237a5&width=1200&height=600&smart=true",
      "published": "2026-07-07 02:27:38",
      "category": [
        "top",
        "health"
      ],
      "country": [
        "united states of america"
      ]
    }
  ]
}