{
  "status": "success",
  "totalResults": 1,
  "results": [
    {
      "title": "Dr Florez on the FDA Approval of Zidesamtinib in Pretreated ROS1+ NSCLC",
      "description": "Narjust Florez, MD, discusses how the FDA approval of zidesamtinib in locally advanced or metastatic ROS1-positive NSCLC is an example of the fast pace of clinical oncology.",
      "link": "https://www.onclive.com/view/dr-florez-on-the-fda-approval-of-zidesamtinib-in-pretreated-ros1-nsclc",
      "source": "Onclive",
      "image": "https://cdn.sanity.io/images/0vv8moc6/onclive/ba5fea7a421c67dd5af18287ecb28594d54da6a5-1280x720.png",
      "published": "2026-07-23 21:19:00",
      "category": [
        "health",
        "top"
      ],
      "country": [
        "united states of america"
      ]
    }
  ]
}